moveread/pipelines/input_validation/__init__.py
moveread/pipelines/input_validation/__init__.pyi
moveread/pipelines/input_validation/_types.py
moveread/pipelines/input_validation/api.py
moveread/pipelines/input_validation/spec.py
moveread/pipelines/input_validation/scripts/__init__.py
moveread/pipelines/input_validation/scripts/__init__.pyi
moveread/pipelines/input_validation/scripts/cli.py
moveread/pipelines/input_validation/scripts/clientgen_cli.py
moveread/pipelines/input_validation/scripts/core.py
moveread_pipelines_input_validation-0.2.8.dist-info/METADATA
moveread_pipelines_input_validation-0.2.8.dist-info/WHEEL
moveread_pipelines_input_validation-0.2.8.dist-info/entry_points.txt
moveread_pipelines_input_validation-0.2.8.dist-info/top_level.txt
moveread_pipelines_input_validation-0.2.8.dist-info/RECORD
