Metadata-Version: 2.1
Name: moveread-pipelines-input-validation
Version: 0.2.8
Summary: Moveread Input Validation pipeline
Author-email: Marcel Claramunt <marcel@moveread.com>
Project-URL: repo, https://github.com/moveread/pipelines.git
Requires-Python: >=3.10
Requires-Dist: python-kv
Requires-Dist: pipeteer
Requires-Dist: chess-pairings
Requires-Dist: lazy-loader
Requires-Dist: fastapi
Requires-Dist: pure-cv
